sphinx_disqus/__init__.py
sphinx_disqus/_static/disqus.js
sphinx_disqus/disqus.py
sphinx_disqus-1.3.0.dist-info/COPYING
sphinx_disqus-1.3.0.dist-info/LICENSE
sphinx_disqus-1.3.0.dist-info/METADATA
sphinx_disqus-1.3.0.dist-info/WHEEL
sphinx_disqus-1.3.0.dist-info/RECORD
